investpy/__init__.py
investpy/calculos.py
investpy/dados.py
investpy/visualizacao.py
investimentpyfiap-1.0.1.dist-info/METADATA
investimentpyfiap-1.0.1.dist-info/WHEEL
investimentpyfiap-1.0.1.dist-info/top_level.txt
investimentpyfiap-1.0.1.dist-info/RECORD
