Metadata-Version: 2.4
Name: investimentpyFIAP
Version: 1.0.1
Summary: Uma biblioteca para análise de investimentos
Home-page: https://github.com/LeLudwig18/investimentpyFIAP
Author: Leandro Ludwig
Author-email: leandro.ludwig@live.com
License: MIT
Dynamic: author
Dynamic: author-email
Dynamic: description
Dynamic: description-content-type
Dynamic: home-page
Dynamic: license
Dynamic: summary
